cpematcher/__init__.py
cpematcher/core.py
cpematcher/utils.py
cpematcher/version.py
cpematcher-0.0.8.dist-info/LICENSE.md
cpematcher-0.0.8.dist-info/METADATA
cpematcher-0.0.8.dist-info/WHEEL
cpematcher-0.0.8.dist-info/top_level.txt
cpematcher-0.0.8.dist-info/RECORD
